{
  "project_info": {
    "project_number": "[project_id]",
    "firebase_url": "[firebase_url]",
    "project_id": "[project_name]",
    "storage_bucket": "[bucket]"
  },
  "client": [
    {
      "client_info": {
        "mobilesdk_app_id": "1:00000000000:android:00000000000000",
        "android_client_info": {
          "package_name": "com.playone.mobile.debug"
        }
      },
      "oauth_client": [
        {
          "client_id": "",
          "client_type": 1,
          "android_info": {
            "package_name": "com.playone.mobile.debug",
            "certificate_hash": ""
          }
        },
        {
          "client_id": "",
          "client_type": 1,
          "android_info": {
            "package_name": "com.playone.mobile.debug",
            "certificate_hash": ""
          }
        },
        {
          "client_id": "",
          "client_type": 3
        }
      ],
      "api_key": [
        {
          "current_key": ""
        }
      ],
      "services": {
        "analytics_service": {
          "status": 1
        },
        "appinvite_service": {
          "status": 2,
          "other_platform_oauth_client": [
            {
              "client_id": "",
              "client_type": 3
            }
          ]
        },
        "ads_service": {
          "status": 2
        }
      }
    }
  ],
  "configuration_version": "1"
}